pycommerce/__init__.py
pycommerce-0.0.2.dist-info/LICENSE
pycommerce-0.0.2.dist-info/METADATA
pycommerce-0.0.2.dist-info/WHEEL
pycommerce-0.0.2.dist-info/top_level.txt
pycommerce-0.0.2.dist-info/RECORD
