Metadata-Version: 2.1
Name: pycommerce
Version: 0.0.2
Summary: The fundamental package for commerce with Python.
Home-page: https://github.com/pycommerce/pycommerce
Author: Joridos
License: UNKNOWN
Platform: UNKNOWN
Classifier: Programming Language :: Python :: 3
Classifier: License :: OSI Approved :: BSD License
Classifier: Operating System :: OS Independent
Requires-Python: >=3.8
